odoo/addons/sale_order_note_template/README.rst
odoo/addons/sale_order_note_template/__init__.py
odoo/addons/sale_order_note_template/__manifest__.py
odoo/addons/sale_order_note_template/i18n/it.po
odoo/addons/sale_order_note_template/i18n/sale_order_note_template.pot
odoo/addons/sale_order_note_template/i18n/tr.po
odoo/addons/sale_order_note_template/models/__init__.py
odoo/addons/sale_order_note_template/models/sale_order.py
odoo/addons/sale_order_note_template/models/sale_terms_template.py
odoo/addons/sale_order_note_template/readme/CONTRIBUTOR.rst
odoo/addons/sale_order_note_template/readme/DESCRIPTION.md
odoo/addons/sale_order_note_template/readme/ROADMAP.md
odoo/addons/sale_order_note_template/security/ir.model.access.csv
odoo/addons/sale_order_note_template/static/description/icon.png
odoo/addons/sale_order_note_template/static/description/index.html
odoo/addons/sale_order_note_template/tests/__init__.py
odoo/addons/sale_order_note_template/tests/test_sale_order.py
odoo/addons/sale_order_note_template/tests/test_sale_terms_template.py
odoo/addons/sale_order_note_template/views/sale_terms_template.xml
odoo/addons/sale_order_note_template/views/sale_views.xml
odoo_addon_sale_order_note_template-18.0.1.0.0.5.dist-info/METADATA
odoo_addon_sale_order_note_template-18.0.1.0.0.5.dist-info/WHEEL
odoo_addon_sale_order_note_template-18.0.1.0.0.5.dist-info/top_level.txt
odoo_addon_sale_order_note_template-18.0.1.0.0.5.dist-info/RECORD
