Metadata-Version: 2.1
Name: odoo-addon-sale_order_note_template
Version: 18.0.1.0.0.5
Requires-Python: >=3.10
Requires-Dist: odoo==18.0.*
Summary: Add sale orders terms and conditions template that can be used to quickly fullfill sale order terms and conditions
Home-page: https://github.com/OCA/sale-workflow
License: AGPL-3
Author: Pierre Verkest,Odoo Community Association (OCA)
Author-email: support@odoo-community.org
Classifier: Programming Language :: Python
Classifier: Framework :: Odoo
Classifier: Framework :: Odoo :: 18.0
Classifier: License :: OSI Approved :: GNU Affero General Public License v3
